liver_annotation/__init__.py
liver_annotation-0.1.2.dist-info/LICENSE
liver_annotation-0.1.2.dist-info/METADATA
liver_annotation-0.1.2.dist-info/WHEEL
liver_annotation-0.1.2.dist-info/top_level.txt
liver_annotation-0.1.2.dist-info/RECORD
