Metadata-Version: 2.1
Name: liver-annotation
Version: 0.1.2
Summary: A machine learning model for classification of cells and annotation of clusters in scRNA-seq data from liver samples.
Home-page: https://github.com/mThkTrn/liver_annotation
Author: Madhavendra Thakur
Author-email: madhavendra.thakur@gmail.com
License: UNKNOWN
Platform: UNKNOWN
Classifier: Programming Language :: Python :: 3
Classifier: License :: OSI Approved :: MIT License
Classifier: Operating System :: OS Independent
Requires-Python: >=3.10
License-File: LICENSE
Requires-Dist: joblib (>=1.4.2)
Requires-Dist: torch (>=2.1.2)
Requires-Dist: scikit-learn (>=1.2.2)
Requires-Dist: scipy (>=1.11.4)
